Workbook

Sheet Final Table
A1: Startup Portfolio | B1: Press/Public Announcement | C1: Date of Wire | D1: Capital Invested | E1: FX Conversion | F1: Inflation Factor | G1: Capital Invested ($ ATOI) | H1: Capital Invested ($ 2025) | I1: Shares | J1: Shares Outstanding (M) | K1: PPS ($ ATOI) | L1: PPS ($ 2025) | M1: Round Size ($M 2025) | N1: Round Size ($M ATOI) | O1: Pre Money Val ($M 2025) | P1: Pre Money Val ($M ATOI) | Q1: Post Money Val ($M 2025) | R1: Post Money Val ($M ATOI) | S1: PNP Equity | T1: Press/Public Announcement | U1: Valuation Date | V1: Date of Second Wire | W1: Capital Invested ($ ATOI) | X1: Inflation Factor | Y1: Capital Invested ($ 2025) | Z1: Shares | AA1: Shares Outstanding (M) | AB1: PPS ($ ATOI) | AC1: PPS ($ 2025) | AD1: Round Size ($M 2025) | AE1: Round Size ($M ATOI) | AF1: Pre Money Val ($M 2025) | AG1: Pre Money Val ($M ATOI) | AH1: Post Money Val ($M 2025) | AI1: Post Money Val ($M ATOI) | AJ1: PNP Equity | AK1: Equity Value | AL1: Equity Value ($ 2025) | AM1: % Capital Invested | AN1: RVPI | AO1: Adjusted RVPI | AP1: Round 1 Multiple | AQ1: Adjusted Rd 1 Multiple | AR1: IRR | AS1: Benchmark IRR | AT1: Alpha | AU1: Adjusted IRR | AV1: Adjusted Benchmark IRR | AW1: Adjusted Alpha | AX1: Sector
A2: Start up 1 | B2: 41797 | C2: 41777 | D2: 86789 | E2: 1 | F2: 1.3652795 | G2: 86789 | H2: 118491.25 | I2: 449185 | J2: 207.02393 | K2: 0.19321438 | L2: 0.26379163 | M2: 19.156323 | N2: 14.031063 | O2: 0.00042173448 | P2: 25.968937 | Q2: 6.8263976 | R2: 40 | S2: 0.002169725 | T2: 43952 | U2: 43944 | V2: 43944 | W2: 2157352.8 | X2: 1.266825 | Y2: 2732988.5 | Z2: 3897870.6 | AA2: 225.20332 | AB2: 0.55346959 | AC2: 0.70114912 | AD2: 12.746462 | AE2: 10.061739 | AF2: 122.65148 | AG2: 96.818016 | AH2: 135.39795 | AI2: 106.87975 | AJ2: 0.019302804 | AK2: 2063079 | AL2: 2613560.1 | AM2: 0.28354604 | AN2: 0.91931755 | AO2: 23.770856 | AP2: 2.8645362 | AQ2: 0.7556407 | AR2: -0.17202846 | AS2: 0.1073272 | AT2: -0.27935567 | AU2: -0.18723581 | AV2: 0.086988935 | AW2: -0.27422475 | AX2: AI & Data
A3: Start up 2 | B3: 41930 | C3: 41914 | D3: 125403 | E3: 1 | F3: 1.3679649 | G3: 125403 | H3: 171546.9 | I3: 375516 | J3: 14.972369 | K3: 0.33394849 | L3: 0.45682979 | M3: 3.5554428 | N3: 2.5990747 | O3: 3.2843815 | P3: 2.4009253 | Q3: 41.038946 | R3: 5 | S3: 0.0250806 | T3: 44476 | U3: 44466 | V3: 44466 | W3: 81537.495 | X3: 1.1840618 | Y3: 96545.435 | Z3: 623120.67 | AA3: 17.778198 | AB3: 0.13085346 | AC3: 0.15493859 | AD3: 0.4347312 | AE3: 0.36715245 | AF3: 1.9801722 | AG3: 1.6723554 | AH3: 2.4149034 | AI3: 2.0395078 | AJ3: 0.056171984 | AK3: 114563.2 | AL3: 135649.91 | AM3: 0.026146814 | AN3: 0.55360456 | AO3: 0.91355167 | AP3: 0.39183726 | AQ3: 0.17900293 | AR3: 0.31161284 | AS3: 0.17326213 | AT3: 0.13835071 | AU3: 0.27982619 | AV3: 0.14482839 | AW3: 0.13499781 | AX3: Fintech
A4: Start up 3 | B4: 42394 | C4: 42374 | D4: 161661 | E4: 1.0746 | F4: 1.37095 | G4: 173720.91 | H4: 238162.69 | I4: 416727 | J4: 71.964912 | K4: 0.41686982 | L4: 0.5715077 | M4: 5.5957928 | N4: 4.0816898 | O4: 35.532708 | P4: 25.91831 | Q4: 20.564251 | R4: 30 | S4: 0.005790697 | U4: 44051 | W4: 0 | X4: 1.2496249 | Y4: 0 | Z4: 0 | AA4: 84.832754 | AB4: 5.0109432 | AC4: 6.2617993 | AD4: 80.575844 | AE4: 64.480025 | AF4: 405.35779 | AG4: 324.38357 | AH4: 485.93363 | AI4: 388.8636 | AJ4: 0.0049123361 | AK4: 1910228.7 | AL4: 2387069.3 | AM4: 0.021949538 | AN4: 10.995963 | AO4: 10.995884 | AP4: 12.020403 | AQ4: 6.8697528 | AR4: 1.3404428 | AS4: 0.10093097 | AT4: 1.2395118 | AU4: 1.3214269 | AV4: 0.091986009 | AW4: 1.2294409 | AX4: Climate-Tech
A5: Start up 4 | B5: 42243 | C5: 42227 | D5: 160214 | E5: 1 | F5: 1.3628963 | G5: 160214 | H5: 218355.07 | I5: 495644 | J5: 46.404559 | K5: 0.3232441 | L5: 0.4405482 | M5: 7.3962103 | N5: 5.4268327 | O5: 13.047235 | P5: 9.5731673 | Q5: 13.628963 | R5: 15 | S5: 0.010680933 | U5: 43860 | W5: 0 | X5: 1.2590563 | Y5: 0 | Z5: 0 | AA5: 49.846582 | AB5: 1.1409535 | AC5: 1.4365247 | AD5: 4.9445511 | AE5: 3.9271884 | AF5: 52.458654 | AG5: 41.66506 | AH5: 57.403205 | AI5: 45.592248 | AJ5: 0.0099433899 | AK5: 453341.5 | AL5: 570782.45 | AM5: 0.020242948 | AN5: 2.8295998 | AO5: 2.8295775 | AP5: 3.5296963 | AQ5: 1.5550013 | AR5: 0.41199495 | AS5: 0.10365762 | AT5: 0.30833733 | AU5: 0.3859824 | AV5: 0.083325431 | AW5: 0.30265697 | AX5: Biotech
A6: Start up 5 | B6: 41535 | C6: 41527 | D6: 100809 | E6: 1 | F6: 1.3871509 | G6: 100809 | H6: 139837.3 | I6: 453378 | J6: 44.973961 | K6: 0.22235089 | L6: 0.30843424 | M6: 4.9939468 | N6: 3.6001467 | O6: 8.8775623 | P6: 6.3998533 | Q6: 13.871509 | R6: 10 | S6: 0.0100809 | T6: 44152 | U6: 44134 | V6: 44134 | W6: 94537.208 | X6: 1.2473693 | Y6: 117922.81 | Z6: 818084.25 | AA6: 49.113931 | AB6: 0.11555926 | AC6: 0.14414507 | AD6: 0.59675634 | AE6: 0.47841192 | AF6: 4.9428518 | AG6: 3.962621 | AH6: 5.5396081 | AI6: 4.4410329 | AJ6: 0.025888016 | AK6: 114969.53 | AL6: 143409.47 | AM6: 0.024681882 | AN6: 0.58854243 | AO6: 1.1404548 | AP6: 0.51971575 | AQ6: 0.16029813 | AR6: 0.17259422 | AS6: 0.13277413 | AT6: 0.039820087 | AU6: 0.15783204 | AV6: 0.11851328 | AW6: 0.039318764 | AX6: Biotech
A7: Start up 6 | B7: 42463 | C7: 42455 | D7: 173561 | E7: 1.1163 | F7: 1.3639494 | G7: 193746.14 | H7: 264259.94 | I7: 369598 | J7: 19.076405 | K7: 0.52420777 | L7: 0.71499288 | M7: 6.7270096 | N7: 4.9320081 | O7: 6.9124845 | P7: 5.0679919 | Q7: 47.738229 | R7: 10 | S7: 0.019374614 | U7: 43814 | W7: 0 | X7: 1.2639411 | Y7: 0 | Z7: 0 | AA7: 20.494459 | AB7: 0.25268567 | AC7: 0.3193798 | AD7: 0.45289772 | AE7: 0.35832185 | AF7: 4.7546403 | AG7: 3.7617578 | AH7: 5.207538 | AI7: 4.1200797 | AJ7: 0.018034045 | AK7: 74301.703 | AL7: 93912.976 | AM7: 0.024479715 | AN7: 0.38350029 | AO7: 0.38349779 | AP7: 0.48203342 | AQ7: 0.34465047 | AR7: 0.35625625 | AS7: 0.13893786 | AT7: 0.21731839 | AU7: 0.32885116 | AV7: 0.11592399 | AW7: 0.21292716 | AX7: Climate-Tech
A8: Start up 7 | B8: 42081 | C8: 42069 | D8: 143867 | E8: 1 | F8: 1.3755776 | G8: 143867 | H8: 197900.22 | I8: 490854 | J8: 119.41508 | K8: 0.2930953 | L8: 0.40317532 | M8: 27.329785 | N8: 19.867861 | O8: 20.81543 | P8: 15.132139 | Q8: 41.267327 | R8: 35 | S8: 0.0041104857 | T8: 43837 | U8: 43820 | V8: 43820 | W8: 311970.09 | X8: 1.2639411 | Y8: 394311.82 | Z8: 2652867.4 | AA8: 144.75595 | AB8: 0.11759732 | AC8: 0.14863608 | AD8: 3.7665664 | AE8: 2.9800174 | AF8: 13.996794 | AG8: 11.073929 | AH8: 17.76336 | AI8: 14.053946 | AJ8: 0.021717391 | AK8: 305215.04 | AL8: 385773.84 | AM8: 0.057594757 | AN8: 0.66957044 | AO8: 2.1214897 | AP8: 0.40122553 | AQ8: 0.16176423 | AR8: -0.10285486 | AS8: 0.12172994 | AT8: -0.2245848 | AU8: -0.11441328 | AV8: 0.10727807 | AW8: -0.22169135 | AX8: Fintech
A9: Start up 8 | B9: 42056 | C9: 42045 | D9: 88307 | E9: 1.1319 | F9: 1.3837646 | G9: 99954.693 | H9: 138313.77 | I9: 296812 | J9: 89.083961 | K9: 0.33676096 | L9: 0.4659979 | M9: 18.048664 | N9: 13.043161 | O9: 23.464274 | P9: 16.956839 | Q9: 48.431762 | R9: 30 | S9: 0.0033318231 | T9: 43580 | U9: 43560 | V9: 43560 | W9: 1380235.2 | X9: 1.2709941 | Y9: 1754270.7 | Z9: 690483.28 | AA9: 95.214995 | AB9: 1.9989407 | AC9: 2.5406419 | AD9: 15.576762 | AE9: 12.255574 | AF9: 188.71888 | AG9: 148.48132 | AH9: 204.29565 | AI9: 160.7369 | AJ9: 0.010369115 | AK9: 1666699.4 | AL9: 2118365.1 | AM9: 0.18702114 | AN9: 1.1260038 | AO9: 16.674337 | AP9: 5.9357852 | AQ9: 2.7660635 | AR9: -0.31155268 | AS9: 0.13565291 | AT9: -0.44720559 | AU9: -0.32373611 | AV9: 0.1155553 | AW9: -0.43929141 | AX9: AI & Data
A10: Start up 9 | B10: 42383 | C10: 42373 | D10: 131217 | E10: 1.4715 | F10: 1.37095 | G10: 193085.82 | H10: 264711.01 | I10: 168277 | J10: 30.502992 | K10: 1.1474284 | L10: 1.5730671 | M10: 14.087387 | N10: 10.275638 | O10: 33.895865 | P10: 24.724362 | Q10: 34.273751 | R10: 35 | S10: 0.0055167376 | T10: 43452 | U10: 43445 | V10: 43445 | W10: 2283183.3 | X10: 1.2928238 | Y10: 2951753.6 | Z10: 421561.28 | AA10: 33.295731 | AB10: 5.4160175 | AC10: 7.0019563 | AD10: 19.554639 | AE10: 15.125526 | AF10: 160.33316 | AG10: 124.0178 | AH10: 179.8878 | AI10: 139.14332 | AJ10: 0.017715132 | AK10: 2464942.4 | AL10: 3186736.2 | AM10: 0.31287519 | AN10: 0.99542591 | AO10: 12.76596 | AP10: 4.7201353 | AQ10: 7.4250894 | AR10: 0.44240323 | AS10: 0.1262059 | AT10: 0.31619732 | AU10: 0.42052905 | AV10: 0.10912688 | AW10: 0.31140217 | AX10: AI & Data
A11: Start up 10 | B11: 41793 | C11: 41780 | D11: 194185 | E11: 1.6899 | F11: 1.3652795 | G11: 328153.23 | H11: 448020.89 | I11: 469242 | J11: 35.748696 | K11: 0.69932621 | L11: 0.95477576 | M11: 6.1941547 | N11: 4.5369132 | O11: 27.937834 | P11: 20.463087 | Q11: 0 | R11: 25 | S11: 0.013126129 | U11: 42727 | W11: 0 | X11: 1.3453063 | Y11: 0 | Z11: 0 | AA11: 39.701723 | AB11: 0.27730254 | AC11: 0.37305687 | AD11: 1.4747039 | AE11: 1.0961844 | AF11: 12.144523 | AG11: 9.0273291 | AH11: 13.619227 | AI11: 10.123514 | AJ11: 0.011819185 | AK11: 119651.68 | AL11: 160968.16 | AM11: 0.041461974 | AN11: 0.36462136 | AO11: 0.36461987 | AP11: 0.39652817 | AQ11: 0.37859548 | AR11: 0.13218241 | AS11: 0.14144233 | AT11: -0.0092599154 | AU11: 0.11089444 | AV11: 0.11998023 | AW11: -0.0090857983 | AX11: EdTech

Sheet Valuation Bins
A1: Valuation | B1: Round 1 Count | C1: Round 2 Count
A2: $0-$5M | B2: =COUNTIFS('Final Table'!$Q$2:$Q$11,">=0",'Final Table'!$Q$2:$Q$11,"<=5") -> 1 | C2: =COUNTIFS('Final Table'!$AH$2:$AH$11,">=0",'Final Table'!$AH$2:$AH$11,"<=5") -> 1
A3: $5-$15M | B3: =COUNTIFS('Final Table'!$Q$2:$Q$11,">5",'Final Table'!$Q$2:$Q$11,"<=15") -> 3 | C3: =COUNTIFS('Final Table'!$AH$2:$AH$11,">5",'Final Table'!$AH$2:$AH$11,"<=15") -> 3
A4: $15-$30M | B4: =COUNTIFS('Final Table'!$Q$2:$Q$11,">15",'Final Table'!$Q$2:$Q$11,"<=30") -> 1 | C4: =COUNTIFS('Final Table'!$AH$2:$AH$11,">15",'Final Table'!$AH$2:$AH$11,"<=30") -> 1
A5: $30-$50M | B5: =COUNTIFS('Final Table'!$Q$2:$Q$11,">30",'Final Table'!$Q$2:$Q$11,"<=50") -> 5 | C5: =COUNTIFS('Final Table'!$AH$2:$AH$11,">30",'Final Table'!$AH$2:$AH$11,"<=50") -> 0
A6: $50-$100M | B6: =COUNTIFS('Final Table'!$Q$2:$Q$11,">50",'Final Table'!$Q$2:$Q$11,"<=100") -> 0 | C6: =COUNTIFS('Final Table'!$AH$2:$AH$11,">50",'Final Table'!$AH$2:$AH$11,"<=100") -> 1
A7: $100-$250M | B7: =COUNTIFS('Final Table'!$Q$2:$Q$11,">100",'Final Table'!$Q$2:$Q$11,"<=250") -> 0 | C7: =COUNTIFS('Final Table'!$AH$2:$AH$11,">100",'Final Table'!$AH$2:$AH$11,"<=250") -> 3
A8: $250-$500M | B8: =COUNTIFS('Final Table'!$Q$2:$Q$11,">250",'Final Table'!$Q$2:$Q$11,"<=500") -> 0 | C8: =COUNTIFS('Final Table'!$AH$2:$AH$11,">250",'Final Table'!$AH$2:$AH$11,"<=500") -> 1
A9: $500M-$1B | B9: =COUNTIFS('Final Table'!$Q$2:$Q$11,">500",'Final Table'!$Q$2:$Q$11,"<=1000") -> 0 | C9: =COUNTIFS('Final Table'!$AH$2:$AH$11,">500",'Final Table'!$AH$2:$AH$11,"<=1000") -> 0
A10: $1B+ | B10: =COUNTIFS('Final Table'!$Q$2:$Q$11,">1000") -> 0 | C10: =COUNTIFS('Final Table'!$AH$2:$AH$11,">1000") -> 0

Sheet Portfolio Metrics
A1: Rd 1 Diversification Index | B1: Rd 2 Diversification Index | C1: Portfolio RVPI | D1: Adjusted Portfolio RVPI | E1: Portfolio Valuation Growth | F1: Adjusted Portfolio Valuation Growth | G1: Rd 1 Portfolio Multiple | H1: Adjusted Rd 1 Portfolio Multiple | I1: Portfolio IRR | J1: Benchmark Portfolio IRR | K1: Alpha | L1: Adjusted Portfolio IRR | M1: Adjusted Benchmark Portfolio IRR | N1: Adjusted Alpha | O1: Profit | P1: Total Investment
A2: {=1 / SUMPRODUCT(('Final Table'!G2:G11/ SUM('Final Table'!G2:G11))^2)} -> 8.5247661 | B2: {=1 / SUMPRODUCT(('Final Table'!AK2:AK11/ SUM('Final Table'!AK2:AK11))^2)} -> 5.0425906 | C2: =SUM('Final Table'!AK2:AK11)/SUM('Final Table'!G2:G11,'Final Table'!W2:W11) -> 1.1734062 | D2: =SUM('Final Table'!AL2:AL11)/SUM('Final Table'!H2:H11,'Final Table'!Y2:Y11) -> 1.1511444 | E2: =SUM('Final Table'!AI2:AI11)/SUM('Final Table'!R2:R11) -> 3.7276336 | F2: =SUM('Final Table'!AH2:AH11)/SUM('Final Table'!Q2:Q11) -> 4.1378649 | G2: =SUMPRODUCT('Final Table'!I2:I11,'Final Table'!AB2:AB11)/SUM('Final Table'!G2:G11) -> 2.9829061 | H2: =SUMPRODUCT('Final Table'!I2:I11,'Final Table'!AC2:AC11)/SUM('Final Table'!H2:H11) -> 2.7543026 | I2: =XIRR(Table22[Cashflow],Table22[Date]) -> 0.13300828 | J2: =XIRR(Table22[Benchmark Cashflow],Table22[Date]) -> 0.12335958 | K2: =I2-J2 -> 0.0096487045 | L2: =XIRR(Table22[Adjusted Cashflow],Table22[Date]) -> 0.11411168 | M2: =XIRR(Table22[Adjusted Benchmark Cashflow],Table22[Date]) -> 0.10473335 | N2: =L2-M2 -> 0.0093783259 | O2: =SUM('Final Table'!AL:AL)-SUM('Final Table'!Y:Y,'Final Table'!H:H) -> 1548835.5 | P2: =SUM('Final Table'!H2:H11,'Final Table'!Y2:Y11) -> 10247392

Sheet Yearly IRR
A1: Year | B1: IRR | C1: Benchmark IRR
A2: {=_xlfn._xlws.SORT(_xlfn.UNIQUE(YEAR(Table22[Date])))} -> 2013 | B2: {=_xlfn.BYROW(_xlfn.ANCHORARRAY(A2), _xlfn.LAMBDA(_xlpm.y, IFERROR( XIRR( _xlfn._xlws.FILTER(Table22[Adjusted Cashflow], Table22[Date] <= DATE(_xlpm.y,12,31)), _xlfn._xlws.FILTER(Table22[Date], Table22[Date] <= DATE(_xlpm.y,12,31)) ), 0 ) ))} -> 0 | C2: {=_xlfn.BYROW(_xlfn.ANCHORARRAY(A2), _xlfn.LAMBDA(_xlpm.y, IFERROR( XIRR( _xlfn._xlws.FILTER(Table22[Adjusted Benchmark Cashflow], Table22[Date] <= DATE(_xlpm.y,12,31)), _xlfn._xlws.FILTER(Table22[Date], Table22[Date] <= DATE(_xlpm.y,12,31)) ), 0 ) ))} -> 0
A3: 2014 | B3: 0 | C3: 0
A4: 2015 | B4: 0 | C4: 0
A5: 2016 | B5: 2.9802322e-09 | C5: 2.9802322e-09
A6: 2018 | B6: 2.9802322e-09 | C6: 2.9802322e-09
A7: 2019 | B7: 2.9802322e-09 | C7: 2.9802322e-09
A8: 2020 | B8: 0.11212097 | C8: 0.079416916
A9: 2021 | B9: 0.11411168 | C9: 0.10473335

Sheet IRR
A1: Company | B1: Date | C1: Cashflow | D1: Benchmark Cashflow | E1: Adjusted Cashflow | F1: Adjusted Benchmark Cashflow
A2: Startup 1 | B2: ='Final Table'!$C$2 -> 41777 | C2: =-'Final Table'!$G$2 -> -86789 | D2: =-'Final Table'!$G$2 -> -86789 | E2: =VLOOKUP(Table22[[#This Row],[Date]],Table15[],3,TRUE)*Table22[[#This Row],[Cashflow]] -> -118491.25 | F2: =VLOOKUP(Table22[[#This Row],[Date]],Table15[],3,TRUE)*Table22[[#This Row],[Benchmark Cashflow]] -> -118491.25
A3: Startup 1 | B3: ='Final Table'!$V$2 -> 43944 | C3: =-'Final Table'!$W$2 -> -2157352.8 | D3: =-'Final Table'!$W$2 -> -2157352.8 | E3: =VLOOKUP(Table22[[#This Row],[Date]],Table15[],3,TRUE)*Table22[[#This Row],[Cashflow]] -> -2732988.5 | F3: =VLOOKUP(Table22[[#This Row],[Date]],Table15[],3,TRUE)*Table22[[#This Row],[Benchmark Cashflow]] -> -2732988.5
A4: Startup 1 | B4: ='Final Table'!$V$2 -> 43944 | C4: ='Final Table'!$AK$2 -> 2063079 | D4: =(VLOOKUP(B4,'SP500'!A2:B3328,2,TRUE)*(-D2)/VLOOKUP(B2,'SP500'!A2:B3328,2,TRUE))+(VLOOKUP(B4,'SP500'!A2:B3328,2,TRUE)*(-D3)/VLOOKUP(B3,'SP500'!A2:B3328,2,TRUE)) -> 2303313.9 | E4: =VLOOKUP(Table22[[#This Row],[Date]],Table15[],3,TRUE)*Table22[[#This Row],[Cashflow]] -> 2613560.1 | F4: =VLOOKUP(Table22[[#This Row],[Date]],Table15[],3,TRUE)*Table22[[#This Row],[Benchmark Cashflow]] -> 2917895.7
A5: Startup 2 | B5: ='Final Table'!$C$3 -> 41914 | C5: =-'Final Table'!$G$3 -> -125403 | D5: =-'Final Table'!$G$3 -> -125403 | E5: =VLOOKUP(Table22[[#This Row],[Date]],Table15[],3,TRUE)*Table22[[#This Row],[Cashflow]] -> -171546.9 | F5: =VLOOKUP(Table22[[#This Row],[Date]],Table15[],3,TRUE)*Table22[[#This Row],[Benchmark Cashflow]] -> -171546.9
A6: Startup 2 | B6: ='Final Table'!$V$3 -> 44466 | C6: =-'Final Table'!$W$3 -> -81537.495 | D6: =-'Final Table'!$W$3 -> -81537.495 | E6: =VLOOKUP(Table22[[#This Row],[Date]],Table15[],3,TRUE)*Table22[[#This Row],[Cashflow]] -> -96545.435 | F6: =VLOOKUP(Table22[[#This Row],[Date]],Table15[],3,TRUE)*Table22[[#This Row],[Benchmark Cashflow]] -> -96545.435
A7: Startup 2 | B7: ='Final Table'!$V$3 -> 44466 | C7: ='Final Table'!$AK$3 -> 114563.2 | D7: =(VLOOKUP(B7,'SP500'!A2:B3328,2,TRUE)*(-D5)/VLOOKUP(B5,'SP500'!A2:B3328,2,TRUE))+(VLOOKUP(B7,'SP500'!A2:B3328,2,TRUE)*(-D6)/VLOOKUP(B6,'SP500'!A2:B3328,2,TRUE)) -> 409640.03 | E7: =VLOOKUP(Table22[[#This Row],[Date]],Table15[],3,TRUE)*Table22[[#This Row],[Cashflow]] -> 135649.91 | F7: =VLOOKUP(Table22[[#This Row],[Date]],Table15[],3,TRUE)*Table22[[#This Row],[Benchmark Cashflow]] -> 485039.13
A8: Startup 3 | B8: ='Final Table'!$C$4 -> 42374 | C8: =-'Final Table'!$G$4 -> -173720.91 | D8: =-'Final Table'!$G$4 -> -173720.91 | E8: =VLOOKUP(Table22[[#This Row],[Date]],Table15[],3,TRUE)*Table22[[#This Row],[Cashflow]] -> -238162.69 | F8: =VLOOKUP(Table22[[#This Row],[Date]],Table15[],3,TRUE)*Table22[[#This Row],[Benchmark Cashflow]] -> -238162.69
A9: Startup 3 | B9: ='Final Table'!$U$4 -> 44051 | C9: ='Final Table'!$AK$4 -> 1910228.7 | D9: =(VLOOKUP(B9,'SP500'!A2:B3328,2,TRUE)*(-D8)/VLOOKUP(B8,'SP500'!A2:B3328,2,TRUE)) -> 316742.87 | E9: =VLOOKUP(Table22[[#This Row],[Date]],Table15[],3,TRUE)*Table22[[#This Row],[Cashflow]] -> 2387069.3 | F9: =VLOOKUP(Table22[[#This Row],[Date]],Table15[],3,TRUE)*Table22[[#This Row],[Benchmark Cashflow]] -> 395809.77
A10: Startup 4 | B10: ='Final Table'!$C$5 -> 42227 | C10: =-'Final Table'!$G$5 -> -160214 | D10: =-'Final Table'!$G$5 -> -160214 | E10: =VLOOKUP(Table22[[#This Row],[Date]],Table15[],3,TRUE)*Table22[[#This Row],[Cashflow]] -> -218355.07 | F10: =VLOOKUP(Table22[[#This Row],[Date]],Table15[],3,TRUE)*Table22[[#This Row],[Benchmark Cashflow]] -> -218355.07
A11: Startup 4 | B11: ='Final Table'!$U$5 -> 43860 | C11: ='Final Table'!$AK$5 -> 453341.5 | D11: =(VLOOKUP(B11,'SP500'!A2:B3328,2,TRUE)*(-D10)/VLOOKUP(B10,'SP500'!A2:B3328,2,TRUE)) -> 276583.7 | E11: =VLOOKUP(Table22[[#This Row],[Date]],Table15[],3,TRUE)*Table22[[#This Row],[Cashflow]] -> 570782.45 | F11: =VLOOKUP(Table22[[#This Row],[Date]],Table15[],3,TRUE)*Table22[[#This Row],[Benchmark Cashflow]] -> 348234.43
A12: Startup 5 | B12: ='Final Table'!$C$6 -> 41527 | C12: =-'Final Table'!$G$6 -> -100809 | D12: =-'Final Table'!$G$6 -> -100809 | E12: =VLOOKUP(Table22[[#This Row],[Date]],Table15[],3,TRUE)*Table22[[#This Row],[Cashflow]] -> -139837.3 | F12: =VLOOKUP(Table22[[#This Row],[Date]],Table15[],3,TRUE)*Table22[[#This Row],[Benchmark Cashflow]] -> -139837.3
A13: Startup 5 | B13: ='Final Table'!$V$6 -> 44134 | C13: =-'Final Table'!$W$6 -> -94537.208 | D13: =-'Final Table'!$W$6 -> -94537.208 | E13: =VLOOKUP(Table22[[#This Row],[Date]],Table15[],3,TRUE)*Table22[[#This Row],[Cashflow]] -> -117922.81 | F13: =VLOOKUP(Table22[[#This Row],[Date]],Table15[],3,TRUE)*Table22[[#This Row],[Benchmark Cashflow]] -> -117922.81
A14: Startup 5 | B14: ='Final Table'!$V$6 -> 44134 | C14: ='Final Table'!$AK$6 -> 114969.53 | D14: =(VLOOKUP(B14,'SP500'!A12:B3338,2,TRUE)*(-D12)/VLOOKUP(B12,'SP500'!A12:B3338,2,TRUE))+(VLOOKUP(B14,'SP500'!A12:B3338,2,TRUE)*(-D13)/VLOOKUP(B13,'SP500'!A12:B3338,2,TRUE)) -> 320745.49 | E14: =VLOOKUP(Table22[[#This Row],[Date]],Table15[],3,TRUE)*Table22[[#This Row],[Cashflow]] -> 143409.47 | F14: =VLOOKUP(Table22[[#This Row],[Date]],Table15[],3,TRUE)*Table22[[#This Row],[Benchmark Cashflow]] -> 400088.08
A15: Startup 6 | B15: ='Final Table'!$C$7 -> 42455 | C15: =-'Final Table'!$G$7 -> -193746.14 | D15: =-'Final Table'!$G$7 -> -193746.14 | E15: =VLOOKUP(Table22[[#This Row],[Date]],Table15[],3,TRUE)*Table22[[#This Row],[Cashflow]] -> -264259.94 | F15: =VLOOKUP(Table22[[#This Row],[Date]],Table15[],3,TRUE)*Table22[[#This Row],[Benchmark Cashflow]] -> -264259.94
A16: Startup 6 | B16: ='Final Table'!$U$7 -> 43814 | C16: ='Final Table'!$AK$7 -> 74301.703 | D16: =(VLOOKUP(B16,'SP500'!A7:B3333,2,TRUE)*(-D15)/VLOOKUP(B15,'SP500'!A7:B3333,2,TRUE)) -> 325206.73 | E16: =VLOOKUP(Table22[[#This Row],[Date]],Table15[],3,TRUE)*Table22[[#This Row],[Cashflow]] -> 93912.976 | F16: =VLOOKUP(Table22[[#This Row],[Date]],Table15[],3,TRUE)*Table22[[#This Row],[Benchmark Cashflow]] -> 411042.15
A17: Startup 7 | B17: ='Final Table'!$C$8 -> 42069 | C17: =-'Final Table'!$G$8 -> -143867 | D17: =-'Final Table'!$G$8 -> -143867 | E17: =VLOOKUP(Table22[[#This Row],[Date]],Table15[],3,TRUE)*Table22[[#This Row],[Cashflow]] -> -197900.22 | F17: =VLOOKUP(Table22[[#This Row],[Date]],Table15[],3,TRUE)*Table22[[#This Row],[Benchmark Cashflow]] -> -197900.22
A18: Startup 7 | B18: ='Final Table'!$V$8 -> 43820 | C18: =-'Final Table'!$W$8 -> -311970.09 | D18: =-'Final Table'!$W$8 -> -311970.09 | E18: =VLOOKUP(Table22[[#This Row],[Date]],Table15[],3,TRUE)*Table22[[#This Row],[Cashflow]] -> -394311.82 | F18: =VLOOKUP(Table22[[#This Row],[Date]],Table15[],3,TRUE)*Table22[[#This Row],[Benchmark Cashflow]] -> -394311.82
A19: Startup 7 | B19: ='Final Table'!$V$8 -> 43820 | C19: ='Final Table'!$AK$8 -> 305215.04 | D19: =(VLOOKUP(B19,'SP500'!A17:B3343,2,TRUE)*(-D17)/VLOOKUP(B17,'SP500'!A17:B3343,2,TRUE))+(VLOOKUP(B19,'SP500'!A17:B3343,2,TRUE)*(-D18)/VLOOKUP(B18,'SP500'!A17:B3343,2,TRUE)) -> 558803.14 | E19: =VLOOKUP(Table22[[#This Row],[Date]],Table15[],3,TRUE)*Table22[[#This Row],[Cashflow]] -> 385773.84 | F19: =VLOOKUP(Table22[[#This Row],[Date]],Table15[],3,TRUE)*Table22[[#This Row],[Benchmark Cashflow]] -> 706294.25
A20: Startup 8 | B20: ='Final Table'!$C$9 -> 42045 | C20: =-'Final Table'!$G$9 -> -99954.693 | D20: =-'Final Table'!$G$9 -> -99954.693 | E20: =VLOOKUP(Table22[[#This Row],[Date]],Table15[],3,TRUE)*Table22[[#This Row],[Cashflow]] -> -138313.77 | F20: =VLOOKUP(Table22[[#This Row],[Date]],Table15[],3,TRUE)*Table22[[#This Row],[Benchmark Cashflow]] -> -138313.77
A21: Startup 8 | B21: ='Final Table'!$V$9 -> 43560 | C21: =-'Final Table'!$W$9 -> -1380235.2 | D21: =-'Final Table'!$W$9 -> -1380235.2 | E21: =VLOOKUP(Table22[[#This Row],[Date]],Table15[],3,TRUE)*Table22[[#This Row],[Cashflow]] -> -1754270.7 | F21: =VLOOKUP(Table22[[#This Row],[Date]],Table15[],3,TRUE)*Table22[[#This Row],[Benchmark Cashflow]] -> -1754270.7
A22: Startup 8 | B22: ='Final Table'!$V$9 -> 43560 | C22: ='Final Table'!$AK$9 -> 1666699.4 | D22: =(VLOOKUP(B22,'SP500'!A20:B3346,2,TRUE)*(-D20)/VLOOKUP(B20,'SP500'!A20:B3346,2,TRUE))+(VLOOKUP(B22,'SP500'!A20:B3346,2,TRUE)*(-D21)/VLOOKUP(B21,'SP500'!A20:B3346,2,TRUE)) -> 1532558.2 | E22: =VLOOKUP(Table22[[#This Row],[Date]],Table15[],3,TRUE)*Table22[[#This Row],[Cashflow]] -> 2118365.1 | F22: =VLOOKUP(Table22[[#This Row],[Date]],Table15[],3,TRUE)*Table22[[#This Row],[Benchmark Cashflow]] -> 1947872.4
A23: Startup 9 | B23: ='Final Table'!$C$10 -> 42373 | C23: =-'Final Table'!$G$10 -> -193085.82 | D23: =-'Final Table'!$G$10 -> -193085.82 | E23: =VLOOKUP(Table22[[#This Row],[Date]],Table15[],3,TRUE)*Table22[[#This Row],[Cashflow]] -> -264711.01 | F23: =VLOOKUP(Table22[[#This Row],[Date]],Table15[],3,TRUE)*Table22[[#This Row],[Benchmark Cashflow]] -> -264711.01
A24: Startup 9 | B24: ='Final Table'!$V$10 -> 43445 | C24: =-'Final Table'!$W$10 -> -2283183.3 | D24: =-'Final Table'!$W$10 -> -2283183.3 | E24: =VLOOKUP(Table22[[#This Row],[Date]],Table15[],3,TRUE)*Table22[[#This Row],[Cashflow]] -> -2951753.6 | F24: =VLOOKUP(Table22[[#This Row],[Date]],Table15[],3,TRUE)*Table22[[#This Row],[Benchmark Cashflow]] -> -2951753.6
A25: Startup 9 | B25: ='Final Table'!$V$10 -> 43445 | C25: ='Final Table'!$AK$10 -> 2464942.4 | D25: =(VLOOKUP(B25,'SP500'!A23:B3349,2,TRUE)*(-D23)/VLOOKUP(B23,'SP500'!A23:B3349,2,TRUE))+(VLOOKUP(B25,'SP500'!A23:B3349,2,TRUE)*(-D24)/VLOOKUP(B24,'SP500'!A23:B3349,2,TRUE)) -> 2551836.9 | E25: =VLOOKUP(Table22[[#This Row],[Date]],Table15[],3,TRUE)*Table22[[#This Row],[Cashflow]] -> 3186736.2 | F25: =VLOOKUP(Table22[[#This Row],[Date]],Table15[],3,TRUE)*Table22[[#This Row],[Benchmark Cashflow]] -> 3299075.5
A26: Startup 10 | B26: ='Final Table'!$C$11 -> 41780 | C26: =-'Final Table'!$G$11 -> -328153.23 | D26: =-'Final Table'!$G$11 -> -328153.23 | E26: =VLOOKUP(Table22[[#This Row],[Date]],Table15[],3,TRUE)*Table22[[#This Row],[Cashflow]] -> -448020.89 | F26: =VLOOKUP(Table22[[#This Row],[Date]],Table15[],3,TRUE)*Table22[[#This Row],[Benchmark Cashflow]] -> -448020.89
A27: Startup 10 | B27: ='Final Table'!$U$11 -> 42727 | C27: ='Final Table'!$AK$11 -> 119651.68 | D27: =(VLOOKUP(B27,'SP500'!A18:B3344,2,TRUE)*(-D26)/VLOOKUP(B26,'SP500'!A18:B3344,2,TRUE)) -> 415679.98 | E27: =VLOOKUP(Table22[[#This Row],[Date]],Table15[],3,TRUE)*Table22[[#This Row],[Cashflow]] -> 160968.16 | F27: =VLOOKUP(Table22[[#This Row],[Date]],Table15[],3,TRUE)*Table22[[#This Row],[Benchmark Cashflow]] -> 559216.91

Sheet US CPI
A1: Month | B1: CPI | C1: Inflation Factor
A2: 40544 | B2: 220.223 | C2: =$B$178/B2 -> 1.4748687
A3: 40575 | B3: 221.309 | C3: =$B$178/B3 -> 1.4676312
A4: 40603 | B4: 223.467 | C4: =$B$178/B4 -> 1.4534585
A5: 40634 | B5: 224.906 | C5: =$B$178/B5 -> 1.4441589
A6: 40664 | B6: 225.964 | C6: =$B$178/B6 -> 1.4373971
A7: 40695 | B7: 225.722 | C7: =$B$178/B7 -> 1.4389382
A8: 40725 | B8: 225.922 | C8: =$B$178/B8 -> 1.4376643
A9: 40756 | B9: 226.545 | C9: =$B$178/B9 -> 1.4337107
A10: 40787 | B10: 226.889 | C10: =$B$178/B10 -> 1.431537
A11: 40817 | B11: 226.421 | C11: =$B$178/B11 -> 1.4344959
A12: 40848 | B12: 226.23 | C12: =$B$178/B12 -> 1.435707
A13: 40878 | B13: 225.672 | C13: =$B$178/B13 -> 1.439257
... A178: 45901 | B178: 324.8 | C178: =$B$178/B178 -> 1

Sheet SP500
A1: datetime | B1: close | C1: Normalized
A2: 41129 | B2: 2438.16 | C2: =(B2 / $B$2) -> 1
A3: 41130 | B3: 2440.23 | C3: =(B3 / $B$2) -> 1.000849
A4: 41131 | B4: 2445.64 | C4: =(B4 / $B$2) -> 1.0030679
A5: 41134 | B5: 2443.05 | C5: =(B5 / $B$2) -> 1.0020056
A6: 41135 | B6: 2443.16 | C6: =(B6 / $B$2) -> 1.0020507
A7: 41136 | B7: 2446.82 | C7: =(B7 / $B$2) -> 1.0035519
A8: 41137 | B8: 2464.38 | C8: =(B8 / $B$2) -> 1.010754
A9: 41138 | B9: 2469 | C9: =(B9 / $B$2) -> 1.0126489
A10: 41141 | B10: 2468.99 | C10: =(B10 / $B$2) -> 1.0126448
A11: 41142 | B11: 2460.41 | C11: =(B11 / $B$2) -> 1.0091257
A12: 41143 | B12: 2461.12 | C12: =(B12 / $B$2) -> 1.0094169
A13: 41144 | B13: 2441.29 | C13: =(B13 / $B$2) -> 1.0012838
... A3328: 45961 | B3328: 15173.95 | C3328: =(B3328 / $B$2) -> 6.2235251

Sheet FX GBP USD
A1: Date | B1: Price
A2: 40878 | B2: 1.5693
A3: 40879 | B3: 1.5593
A4: 40882 | B4: 1.5651
A5: 40883 | B5: 1.5593
A6: 40884 | B6: 1.571
A7: 40885 | B7: 1.5639
A8: 40886 | B8: 1.5659
A9: 40889 | B9: 1.5585
A10: 40890 | B10: 1.5478
A11: 40891 | B11: 1.5465
A12: 40892 | B12: 1.5507
A13: 40893 | B13: 1.5519
... A2633: 44561 | B2633: 1.3529

Sheet FX EUR USD
A1: Date | B1: Price
A2: 40878 | B2: 1.3463
A3: 40879 | B3: 1.3402
A4: 40882 | B4: 1.3401
A5: 40883 | B5: 1.3401
A6: 40884 | B6: 1.3412
A7: 40885 | B7: 1.3345
A8: 40886 | B8: 1.3372
A9: 40889 | B9: 1.3184
A10: 40890 | B10: 1.3033
A11: 40891 | B11: 1.298
A12: 40892 | B12: 1.3015
A13: 40893 | B13: 1.3033
... A2633: 44561 | B2633: 1.1368

Sheet Randomized Data
B1: Plug and Play - Junior Portfolio Analyst Case Study 2025
B3: Round 1 | T3: Round 2
A4: Startup Portfolio | B4: Press/Public Announcement | C4: Date of Wire | D4: Capital Invested | E4: FX Conversion | F4: Inflation Factor | G4: Capital Invested ($ ATOI) | H4: Capital Invested ($ 2025) | I4: Shares | J4: Shares Outstanding (M) | K4: PPS ($ ATOI) | L4: PPS ($ 2025) | M4: Round Size ($M 2025) | N4: Round Size ($M ATOI) | O4: Pre Money Val ($M 2025) | P4: Pre Money Val ($M ATOI) | Q4: Post Money Val ($M 2025) | R4: Post Money Val ($M ATOI) | S4: PNP Equity | T4: Press/Public Announcement | U4: Valuation Date | V4: Date of Second Wire | W4: Capital Invested ($ ATOI) | X4: Inflation Factor | Y4: Capital Invested ($ 2025) | Z4: Shares | AA4: Shares Outstanding (M) | AB4: PPS ($ ATOI) | AC4: PPS ($ 2025) | AD4: Round Size ($M 2025) | AE4: Round Size ($M ATOI) | AF4: Pre Money Val ($M 2025) | AG4: Pre Money Val ($M ATOI) | AH4: Post Money Val ($M 2025) | AI4: Post Money Val ($M ATOI) | AJ4: PNP Equity | AK4: Equity Value | AL4: Equity Value ($ 2025) | AM4: % Capital Invested | AN4: RVPI | AO4: Adjusted RVPI | AP4: Round 1 Multiple | AQ4: Adjusted Rd 1 Multiple | AR4: Sector
A5: Start up 1 | B5: =C5 + RANDBETWEEN(5,20) -> 41677 | C5: =RANDBETWEEN(DATE(2012,12,1),DATE(2016,8,8)) -> 41660 | D5: =ROUND(RANDBETWEEN(50000,200000),0) -> 198288 | E5: 1 | F5: =VLOOKUP(C5,'US CPI'!$A$2:$C$178,3,TRUE) -> 1.3885326 | G5: =D5*E5 -> 198288 | H5: =G5*F5 -> 275329.36 | I5: =RANDBETWEEN(100000,500000) -> 398195 | J5: =R5/K5 -> 20.081649 | K5: =G5/I5 -> 0.49796708 | L5: =K5*F5 -> 0.69144354 | M5: =N5*F5 -> 4.9010825 | N5: =(RAND() * (0.6 - 0.05)+0.05) *R5 -> 3.5296847 | O5: =(RAND() * (0.6 - 0.05)+0.05) *S5 -> 0.008702423 | P5: =R5-N5 -> 6.4703153 | Q5: =R6*F5 -> 13.885326 | R5: =RANDBETWEEN(0.5,8)*5 -> 10 | S5: =I5/(1000000*J5) -> 0.0198288 | T5: =IF(W5>0,V5+RANDBETWEEN(5,20),"") -> 44383 | U5: =IF(V5="",RANDBETWEEN(DATE(2016,12,1),DATE(2021,12,31)),V5) -> 44372 | V5: =IF(W5>0,RANDBETWEEN(DATE(2016,12,1),DATE(2021,12,31)),"") -> 44372 | W5: =AE5*1000000*(RAND()*(0.25-0.1)+0.1) -> 87320.85 | X5: =VLOOKUP(IF(V5="",U5,V5),'US CPI'!$A$2:$C$178,3,TRUE) -> 1.1954537 | Y5: =W5*X5 -> 104388.04 | Z5: =W5/AB5 -> 364341.87 | AA5: =(AE5/AB5)+J5 -> 23.403153 | AB5: =K5* (AI5* (0.8 + RAND() * 0.4 ) / R5) -> 0.23966735 | AC5: =AB5*X5 -> 0.28651123 | AD5: =AE5*X5 -> 0.9516482 | AE5: =(RAND() * (0.3- 0.05)+0.05) *AI5 -> 0.79605607 | AF5: =AH5-AD5 -> 3.8750956 | AG5: =AI5-AE5 -> 3.241527 | AH5: =AI5*X5 -> 4.8267438 | AI5: =IF(RAND()>0.45,RAND()*(1-0.4)+0.4*R5,(1+14*RAND())*R5) -> 4.0375831 | AJ5: =(Z5+I5)/(1000000*AA5) -> 0.032582655 | AK5: =AI5*1000000*AJ5 -> 131555.18 | AL5: =AK5*X5 -> 157268.13 | AM5: =(G5+W5)/SUM($G$5:$G$14,$W$5:$W$14) -> 0.029078068 | AN5: =AK5/(G5+W5) -> 0.4606131 | AO5: =AK5/(G5+X5) -> 0.66345107 | AP5: =I5*AB5/G5 -> 0.48129156 | AQ5: =H5*AB5/G5 -> 0.33278594 | AR5: AI & Data
A6: Start up 2 | B6: =C6 + RANDBETWEEN(5,20) -> 41534 | C6: =RANDBETWEEN(DATE(2012,12,1),DATE(2016,8,8)) -> 41515 | D6: =ROUND(RANDBETWEEN(50000,200000),0) -> 55855 | E6: 1 | F6: =VLOOKUP(C6,'US CPI'!$A$2:$C$178,3,TRUE) -> 1.3887642 | G6: =D6*E6 -> 55855 | H6: =G6*F6 -> 77569.423 | I6: =RANDBETWEEN(100000,500000) -> 453657 | J6: =R6/K6 -> 81.220482 | K6: =G6/I6 -> 0.12312165 | L6: =K6*F6 -> 0.17098694 | M6: =N6*F6 -> 4.4162584 | N6: =(RAND() * (0.6 - 0.05)+0.05) *R6 -> 3.1799916 | O6: =P6*F6 -> 9.4713834 | P6: =R6-N6 -> 6.8200084 | Q6: =R7*F6 -> 20.831463 | R6: =RANDBETWEEN(0.5,8)*5 -> 10 | S6: =I6/(1000000*J6) -> 0.0055855 | T6: =IF(W6>0,V6+RANDBETWEEN(5,20),"") -> 43598 | U6: =IF(V6="",RANDBETWEEN(DATE(2016,12,1),DATE(2021,12,31)),V6) -> 43591 | V6: =IF(W6>0,RANDBETWEEN(DATE(2016,12,1),DATE(2021,12,31)),"") -> 43591 | W6: =AE6*1000000*(RAND()*(0.25-0.1)+0.1) -> 2121586.3 | X6: =VLOOKUP(IF(V6="",U6,V6),'US CPI'!$A$2:$C$178,3,TRUE) -> 1.2682942 | Y6: =W6*X6 -> 2690795.6 | Z6: =W6/AB6 -> 1242925.4 | AA6: =(AE6/AB6)+J6 -> 87.64007 | AB6: =K6* (AI6* (0.8 + RAND() * 0.4 ) / R6) -> 1.7069298 | AC6: =AB6*X6 -> 2.1648891 | AD6: =AE6*X6 -> 13.897697 | AE6: =(RAND() * (0.25 - 0.05)+0.05) *AI6 -> 10.957787 | AF6: =AH6-AD6 -> 159.35915 | AG6: =AI6-AE6 -> 125.64841 | AH6: =AI6*X6 -> 173.25685 | AI6: =IF(RAND()>0.45,RAND()*(1-0.4)+0.4*R6,(1+14*RAND())*R6) -> 136.6062 | AJ6: =(Z6+I6)/(1000000*AA6) -> 0.019358524 | AK6: =AI6*1000000*AJ6 -> 2644494.2 | AL6: =AK6*X6 -> 3353996.7 | AM6: =(G6+W6)/SUM($G$5:$G$14,$W$5:$W$14) -> 0.22168706 | AN6: =AK6/(G6+W6) -> 1.2144962 | AO6: =AK6/(G6+X6) -> 47.344628 | AP6: =I6*AB6/G6 -> 13.863766 | AQ6: =H6*AB6/G6 -> 2.3705229 | AR6: Fintech
A7: Start up 3 | B7: =C7 + RANDBETWEEN(5,20) -> 41887 | C7: =RANDBETWEEN(DATE(2012,12,1),DATE(2016,8,8)) -> 41875 | D7: =ROUND(RANDBETWEEN(50000,200000),0) -> 83910 | E7: =VLOOKUP(C7,'FX EUR USD'!$A$2:$B$2663,2,TRUE) -> 1.3242 | F7: =VLOOKUP(C7,'US CPI'!$A$2:$C$178,3,TRUE) -> 1.3655551 | G7: =D7*E7 -> 111113.62 | H7: =G7*F7 -> 151731.77 | I7: =RANDBETWEEN(100000,500000) -> 289673 | J7: =R7/K7 -> 39.104971 | K7: =G7/I7 -> 0.38358294 | L7: =K7*F7 -> 0.52380363 | M7: =N7*F7 -> 10.057757 | N7: =(RAND() * (0.6 - 0.05)+0.05) *R7 -> 7.3653253 | O7: =P7*F7 -> 10.425569 | P7: =R7-N7 -> 7.6346747 | Q7: =R8*F7 -> 40.966652 | R7: =RANDBETWEEN(0.5,8)*5 -> 15 | S7: =I7/(1000000*J7) -> 0.0074075748 | T7: =IF(W7>0,V7+RANDBETWEEN(5,20),"") | U7: =IF(V7="",RANDBETWEEN(DATE(2016,12,1),DATE(2021,12,31)),V7) -> 43659 | V7: =IF(W7>0,RANDBETWEEN(DATE(2016,12,1),DATE(2021,12,31)),"") | W7: 0 | X7: =VLOOKUP(IF(V7="",U7,V7),'US CPI'!$A$2:$C$178,3,TRUE) -> 1.2659264 | Y7: =W7*X7 -> 0 | Z7: =W7/AB7 -> 0 | AA7: =(AE7/AB7)+J7 -> 45.680537 | AB7: =K7* (AI7* (0.8 + RAND() * 0.4 ) / R7) -> 0.16602522 | AC7: =AB7*X7 -> 0.2101757 | AD7: =AE7*X7 -> 1.3820242 | AE7: =(RAND() * (0.25 - 0.05)+0.05) *AI7 -> 1.0917098 | AF7: =AH7-AD7 -> 6.596963 | AG7: =AI7-AE7 -> 5.2111742 | AH7: =AI7*X7 -> 7.9789872 | AI7: =IF(RAND()>0.45,RAND()*(1-0.4)+0.4*R7,(1+14*RAND())*R7) -> 6.302884 | AJ7: =(Z7+I7)/(1000000*AA7) -> 0.0063412783 | AK7: =AI7*1000000*AJ7 -> 39968.341 | AL7: =AK7*X7 -> 50596.978 | AM7: =(G7+W7)/SUM($G$5:$G$14,$W$5:$W$14) -> 0.011312568 | AN7: =AK7/(G7+W7) -> 0.35970694 | AO7: =AK7/(G7+X7) -> 0.35970285 | AP7: =I7*AB7/G7 -> 0.43282742 | AQ7: =H7*AB7/G7 -> 0.22671657 | AR7: Climate-Tech
A8: Start up 4 | B8: =C8 + RANDBETWEEN(5,20) -> 41600 | C8: =RANDBETWEEN(DATE(2012,12,1),DATE(2016,8,8)) -> 41594 | D8: =ROUND(RANDBETWEEN(50000,200000),0) -> 61145 | E8: 1 | F8: =VLOOKUP(C8,'US CPI'!$A$2:$C$178,3,TRUE) -> 1.3935787 | G8: =D8*E8 -> 61145 | H8: =G8*F8 -> 85210.371 | I8: =RANDBETWEEN(100000,500000) -> 298863 | J8: =R8/K8 -> 146.63325 | K8: =G8/I8 -> 0.20459207 | L8: =K8*F8 -> 0.28511516 | M8: =N8*F8 -> 9.7796985 | N8: =(RAND() * (0.6 - 0.05)+0.05) *R8 -> 7.0176864 | O8: =P8*F8 -> 32.027663 | P8: =R8-N8 -> 22.982314 | Q8: =R9*F8 -> 6.9678936 | R8: =RANDBETWEEN(0.5,8)*5 -> 30 | S8: =I8/(1000000*J8) -> 0.0020381667 | T8: =IF(W8>0,V8+RANDBETWEEN(5,20),"") | U8: =IF(V8="",RANDBETWEEN(DATE(2016,12,1),DATE(2021,12,31)),V8) -> 42891 | V8: =IF(W8>0,RANDBETWEEN(DATE(2016,12,1),DATE(2021,12,31)),"") | W8: 0 | X8: =VLOOKUP(IF(V8="",U8,V8),'US CPI'!$A$2:$C$178,3,TRUE) -> 1.3259578 | Y8: =W8*X8 -> 0 | Z8: =W8/AB8 -> 0 | AA8: =(AE8/AB8)+J8 -> 157.19369 | AB8: =K8* (AI8* (0.8 + RAND() * 0.4 ) / R8) -> 2.7169775 | AC8: =AB8*X8 -> 3.6025976 | AD8: =AE8*X8 -> 38.045038 | AE8: =(RAND() * (0.25 - 0.05)+0.05) *AI8 -> 28.692494 | AF8: =AH8-AD8 -> 452.81017 | AG8: =AI8-AE8 -> 341.49666 | AH8: =AI8*X8 -> 490.85521 | AI8: =IF(RAND()>0.45,RAND()*(1-0.4)+0.4*R8,(1+14*RAND())*R8) -> 370.18916 | AJ8: =(Z8+I8)/(1000000*AA8) -> 0.0019012404 | AK8: =AI8*1000000*AJ8 -> 703818.57 | AL8: =AK8*X8 -> 933233.75 | AM8: =(G8+W8)/SUM($G$5:$G$14,$W$5:$W$14) -> 0.0062252219 | AN8: =AK8/(G8+W8) -> 11.510648 | AO8: =AK8/(G8+X8) -> 11.510398 | AP8: =I8*AB8/G8 -> 13.279975 | AQ8: =H8*AB8/G8 -> 3.786322 | AR8: Biotech
A9: Start up 5 | B9: =C9 + RANDBETWEEN(5,20) -> 41511 | C9: =RANDBETWEEN(DATE(2012,12,1),DATE(2016,8,8)) -> 41504 | D9: =ROUND(RANDBETWEEN(50000,200000),0) -> 62923 | E9: 1 | F9: =VLOOKUP(C9,'US CPI'!$A$2:$C$178,3,TRUE) -> 1.3887642 | G9: =D9*E9 -> 62923 | H9: =G9*F9 -> 87385.208 | I9: =RANDBETWEEN(100000,500000) -> 266941 | J9: =R9/K9 -> 21.211719 | K9: =G9/I9 -> 0.23571875 | L9: =K9*F9 -> 0.32735776 | M9: =N9*F9 -> 2.1589562 | N9: =(RAND() * (0.6 - 0.05)+0.05) *R9 -> 1.5545881 | O9: =P9*F9 -> 4.7848647 | P9: =R9-N9 -> 3.4454119 | Q9: =R10*F9 -> 13.887642 | R9: =RANDBETWEEN(0.5,8)*5 -> 5 | S9: =I9/(1000000*J9) -> 0.0125846 | T9: =IF(W9>0,V9+RANDBETWEEN(5,20),"") -> 43573 | U9: =IF(V9="",RANDBETWEEN(DATE(2016,12,1),DATE(2021,12,31)),V9) -> 43563 | V9: =IF(W9>0,RANDBETWEEN(DATE(2016,12,1),DATE(2021,12,31)),"") -> 43563 | W9: =AE9*1000000*(RAND()*(0.25-0.1)+0.1) -> 90163.568 | X9: =VLOOKUP(IF(V9="",U9,V9),'US CPI'!$A$2:$C$178,3,TRUE) -> 1.2709941 | Y9: =W9*X9 -> 114597.36 | Z9: =W9/AB9 -> 1038101.4 | AA9: =(AE9/AB9)+J9 -> 26.564319 | AB9: =K9* (AI9* (0.8 + RAND() * 0.4 ) / R9) -> 0.086854298 | AC9: =AB9*X9 -> 0.1103913 | AD9: =AE9*X9 -> 0.5908805 | AE9: =(RAND() * (0.25 - 0.05)+0.05) *AI9 -> 0.46489633 | AF9: =AH9-AD9 -> 2.2998275 | AG9: =AI9-AE9 -> 1.8094714 | AH9: =AI9*X9 -> 2.890708 | AI9: =IF(RAND()>0.45,RAND()*(1-0.4)+0.4*R9,(1+14*RAND())*R9) -> 2.2743678 | AJ9: =(Z9+I9)/(1000000*AA9) -> 0.049127643 | AK9: =AI9*1000000*AJ9 -> 111734.33 | AL9: =AK9*X9 -> 142013.67 | AM9: =(G9+W9)/SUM($G$5:$G$14,$W$5:$W$14) -> 0.015585867 | AN9: =AK9/(G9+W9) -> 0.72987675 | AO9: =AK9/(G9+X9) -> 1.7756952 | AP9: =I9*AB9/G9 -> 0.3684658 | AQ9: =H9*AB9/G9 -> 0.12062014 | AR9: Biotech
A10: Start up 6 | B10: =C10 + RANDBETWEEN(5,20) -> 41934 | C10: =RANDBETWEEN(DATE(2012,12,1),DATE(2016,8,8)) -> 41918 | D10: =ROUND(RANDBETWEEN(50000,200000),0) -> 127392 | E10: =VLOOKUP(C10,'FX EUR USD'!$A$2:$B$2663,2,TRUE) -> 1.2652 | F10: =VLOOKUP(C10,'US CPI'!$A$2:$C$178,3,TRUE) -> 1.3679649 | G10: =D10*E10 -> 161176.36 | H10: =G10*F10 -> 220483.59 | I10: =RANDBETWEEN(100000,500000) -> 114919 | J10: =R10/K10 -> 7.1300159 | K10: =G10/I10 -> 1.4025214 | L10: =K10*F10 -> 1.9186 | M10: =N10*F10 -> 4.846958 | N10: =(RAND() * (0.6 - 0.05)+0.05) *R10 -> 3.543189 | O10: =P10*F10 -> 8.8326906 | P10: =R10-N10 -> 6.456811 | Q10: =R11*F10 -> 41.038946 | R10: =RANDBETWEEN(0.5,8)*5 -> 10 | S10: =I10/(1000000*J10) -> 0.016117636 | T10: =IF(W10>0,V10+RANDBETWEEN(5,20),"") | U10: =IF(V10="",RANDBETWEEN(DATE(2016,12,1),DATE(2021,12,31)),V10) -> 44237 | V10: =IF(W10>0,RANDBETWEEN(DATE(2016,12,1),DATE(2021,12,31)),"") | W10: 0 | X10: =VLOOKUP(IF(V10="",U10,V10),'US CPI'!$A$2:$C$178,3,TRUE) -> 1.2349153 | Y10: =W10*X10 -> 0 | Z10: =W10/AB10 -> 0 | AA10: =(AE10/AB10)+J10 -> 7.6866728 | AB10: =K10* (AI10* (0.8 + RAND() * 0.4 ) / R10) -> 0.68454875 | AC10: =AB10*X10 -> 0.84535969 | AD10: =AE10*X10 -> 0.47057526 | AE10: =(RAND() * (0.25 - 0.05)+0.05) *AI10 -> 0.38105875 | AF10: =AH10-AD10 -> 4.9565389 | AG10: =AI10-AE10 -> 4.0136673 | AH10: =AI10*X10 -> 5.4271142 | AI10: =IF(RAND()>0.45,RAND()*(1-0.4)+0.4*R10,(1+14*RAND())*R10) -> 4.394726 | AJ10: =(Z10+I10)/(1000000*AA10) -> 0.014950422 | AK10: =AI10*1000000*AJ10 -> 65703.008 | AL10: =AK10*X10 -> 81137.647 | AM10: =(G10+W10)/SUM($G$5:$G$14,$W$5:$W$14) -> 0.016409495 | AN10: =AK10/(G10+W10) -> 0.40764668 | AO10: =AK10/(G10+X10) -> 0.40764356 | AP10: =I10*AB10/G10 -> 0.48808435 | AQ10: =H10*AB10/G10 -> 0.93643863 | AR10: Climate-Tech
A11: Start up 7 | B11: =C11 + RANDBETWEEN(5,20) -> 41648 | C11: =RANDBETWEEN(DATE(2012,12,1),DATE(2016,8,8)) -> 41637 | D11: =ROUND(RANDBETWEEN(50000,200000),0) -> 53505 | E11: 1 | F11: =VLOOKUP(C11,'US CPI'!$A$2:$C$178,3,TRUE) -> 1.3936983 | G11: =D11*E11 -> 53505 | H11: =G11*F11 -> 74569.829 | I11: =RANDBETWEEN(100000,500000) -> 141787 | J11: =R11/K11 -> 79.499299 | K11: =G11/I11 -> 0.37736182 | L11: =K11*F11 -> 0.52592853 | M11: =N11*F11 -> 24.822128 | N11: =(RAND() * (0.6 - 0.05)+0.05) *R11 -> 17.810259 | O11: =P11*F11 -> 16.988822 | P11: =R11-N11 -> 12.189741 | Q11: =R12*F11 -> 34.842458 | R11: =RANDBETWEEN(0.5,8)*5 -> 30 | S11: =I11/(1000000*J11) -> 0.0017835 | T11: =IF(W11>0,V11+RANDBETWEEN(5,20),"") -> 44536 | U11: =IF(V11="",RANDBETWEEN(DATE(2016,12,1),DATE(2021,12,31)),V11) -> 44522 | V11: =IF(W11>0,RANDBETWEEN(DATE(2016,12,1),DATE(2021,12,31)),"") -> 44522 | W11: =AE11*1000000*(RAND()*(0.25-0.1)+0.1) -> 163799.36 | X11: =VLOOKUP(IF(V11="",U11,V11),'US CPI'!$A$2:$C$178,3,TRUE) -> 1.1685639 | Y11: =W11*X11 -> 191410.02 | Z11: =W11/AB11 -> 1236535.2 | AA11: =(AE11/AB11)+J11 -> 86.679825 | AB11: =K11* (AI11* (0.8 + RAND() * 0.4 ) / R11) -> 0.13246639 | AC11: =AB11*X11 -> 0.15479544 | AD11: =AE11*X11 -> 1.1115127 | AE11: =(RAND() * (0.25 - 0.05)+0.05) *AI11 -> 0.95117836 | AF11: =AH11-AD11 -> 13.248088 | AG11: =AI11-AE11 -> 11.337068 | AH11: =AI11*X11 -> 14.359601 | AI11: =IF(RAND()>0.45,RAND()*(1-0.4)+0.4*R11,(1+14*RAND())*R11) -> 12.288246 | AJ11: =(Z11+I11)/(1000000*AA11) -> 0.015901304 | AK11: =AI11*1000000*AJ11 -> 195399.13 | AL11: =AK11*X11 -> 228336.37 | AM11: =(G11+W11)/SUM($G$5:$G$14,$W$5:$W$14) -> 0.022123932 | AN11: =AK11/(G11+W11) -> 0.89919565 | AO11: =AK11/(G11+X11) -> 3.6518992 | AP11: =I11*AB11/G11 -> 0.35103284 | AQ11: =H11*AB11/G11 -> 0.18461818 | AR11: Fintech
A12: Start up 8 | B12: =C12 + RANDBETWEEN(5,20) -> 42037 | C12: =RANDBETWEEN(DATE(2012,12,1),DATE(2016,8,8)) -> 42025 | D12: =ROUND(RANDBETWEEN(50000,200000),0) -> 112612 | E12: =VLOOKUP(C12,'FX EUR USD'!$A$2:$B$2663,2,TRUE) -> 1.1608 | F12: =VLOOKUP(C12,'US CPI'!$A$2:$C$178,3,TRUE) -> 1.3897744 | G12: =D12*E12 -> 130720.01 | H12: =G12*F12 -> 181671.32 | I12: =RANDBETWEEN(100000,500000) -> 339723 | J12: =R12/K12 -> 64.971499 | K12: =G12/I12 -> 0.3847841 | L12: =K12*F12 -> 0.53476309 | M12: =N12*F12 -> 4.5856141 | N12: =(RAND() * (0.6 - 0.05)+0.05) *R12 -> 3.2995386 | O12: =P12*F12 -> 30.158745 | P12: =R12-N12 -> 21.700461 | Q12: =R13*F12 -> 20.846616 | R12: =RANDBETWEEN(0.5,8)*5 -> 25 | S12: =I12/(1000000*J12) -> 0.0052288004 | T12: =IF(W12>0,V12+RANDBETWEEN(5,20),"") -> 43908 | U12: =IF(V12="",RANDBETWEEN(DATE(2016,12,1),DATE(2021,12,31)),V12) -> 43903 | V12: =IF(W12>0,RANDBETWEEN(DATE(2016,12,1),DATE(2021,12,31)),"") -> 43903 | W12: =AE12*1000000*(RAND()*(0.25-0.1)+0.1) -> 6117664.3 | X12: =VLOOKUP(IF(V12="",U12,V12),'US CPI'!$A$2:$C$178,3,TRUE) -> 1.2583538 | Y12: =W12*X12 -> 7698186.3 | Z12: =W12/AB12 -> 1873713.6 | AA12: =(AE12/AB12)+J12 -> 73.840025 | AB12: =K12* (AI12* (0.8 + RAND() * 0.4 ) / R12) -> 3.2649943 | AC12: =AB12*X12 -> 4.108518 | AD12: =AE12*X12 -> 36.4365 | AE12: =(RAND() * (0.25 - 0.05)+0.05) *AI12 -> 28.955687 | AF12: =AH12-AD12 -> 262.40194 | AG12: =AI12-AE12 -> 208.52794 | AH12: =AI12*X12 -> 298.83844 | AI12: =IF(RAND()>0.45,RAND()*(1-0.4)+0.4*R12,(1+14*RAND())*R12) -> 237.48363 | AJ12: =(Z12+I12)/(1000000*AA12) -> 0.029976109 | AK12: =AI12*1000000*AJ12 -> 7118835.2 | AL12: =AK12*X12 -> 8958013.6 | AM12: =(G12+W12)/SUM($G$5:$G$14,$W$5:$W$14) -> 0.63615306 | AN12: =AK12/(G12+W12) -> 1.1393082 | AO12: =AK12/(G12+X12) -> 54.458125 | AP12: =I12*AB12/G12 -> 8.4852629 | AQ12: =H12*AB12/G12 -> 4.5376054 | AR12: AI & Data
A13: Start up 9 | B13: =C13 + RANDBETWEEN(5,20) -> 42022 | C13: =RANDBETWEEN(DATE(2012,12,1),DATE(2016,8,8)) -> 42015 | D13: =ROUND(RANDBETWEEN(50000,200000),0) -> 100103 | E13: =VLOOKUP(C13, 'FX GBP USD'!$A$2:$B$2633,2, TRUE) -> 1.5158 | F13: =VLOOKUP(C13,'US CPI'!$A$2:$C$178,3,TRUE) -> 1.3897744 | G13: =D13*E13 -> 151736.13 | H13: =G13*F13 -> 210878.98 | I13: =RANDBETWEEN(100000,500000) -> 249397 | J13: =R13/K13 -> 24.654346 | K13: =G13/I13 -> 0.608412 | L13: =K13*F13 -> 0.84555541 | M13: =N13*F13 -> 5.7373933 | N13: =(RAND() * (0.6 - 0.05)+0.05) *R13 -> 4.1282911 | O13: =P13*F13 -> 15.109222 | P13: =R13-N13 -> 10.871709 | Q13: =R14*F13 -> 6.9488719 | R13: =RANDBETWEEN(0.5,8)*5 -> 15 | S13: =I13/(1000000*J13) -> 0.010115742 | T13: =IF(W13>0,V13+RANDBETWEEN(5,20),"") -> 42931 | U13: =IF(V13="",RANDBETWEEN(DATE(2016,12,1),DATE(2021,12,31)),V13) -> 42921 | V13: =IF(W13>0,RANDBETWEEN(DATE(2016,12,1),DATE(2021,12,31)),"") -> 42921 | W13: =AE13*1000000*(RAND()*(0.25-0.1)+0.1) -> 175451.68 | X13: =VLOOKUP(IF(V13="",U13,V13),'US CPI'!$A$2:$C$178,3,TRUE) -> 1.3268733 | Y13: =W13*X13 -> 232802.15 | Z13: =W13/AB13 -> 786904.45 | AA13: =(AE13/AB13)+J13 -> 30.078252 | AB13: =K13* (AI13* (0.8 + RAND() * 0.4 ) / R13) -> 0.2229644 | AC13: =AB13*X13 -> 0.29584551 | AD13: =AE13*X13 -> 1.6046383 | AE13: =(RAND() * (0.25 - 0.05)+0.05) *AI13 -> 1.209338 | AF13: =AH13-AD13 -> 6.4284417 | AG13: =AI13-AE13 -> 4.8448046 | AH13: =AI13*X13 -> 8.03308 | AI13: =IF(RAND()>0.45,RAND()*(1-0.4)+0.4*R13,(1+14*RAND())*R13) -> 6.0541426 | AJ13: =(Z13+I13)/(1000000*AA13) -> 0.034453513 | AK13: =AI13*1000000*AJ13 -> 208586.48 | AL13: =AK13*X13 -> 276767.83 | AM13: =(G13+W13)/SUM($G$5:$G$14,$W$5:$W$14) -> 0.033311255 | AN13: =AK13/(G13+W13) -> 0.637513 | AO13: =AK13/(G13+X13) -> 1.3746539 | AP13: =I13*AB13/G13 -> 0.36646944 | AQ13: =H13*AB13/G13 -> 0.30987021 | AR13: AI & Data
A14: Start up 10 | B14: =C14 + RANDBETWEEN(5,20) -> 42239 | C14: =RANDBETWEEN(DATE(2012,12,1),DATE(2016,8,8)) -> 42231 | D14: =ROUND(RANDBETWEEN(50000,200000),0) -> 50944 | E14: =VLOOKUP(C14, 'FX GBP USD'!$A$2:$B$2633,2, TRUE) -> 1.5643 | F14: =VLOOKUP(C14,'US CPI'!$A$2:$C$178,3,TRUE) -> 1.3628963 | G14: =D14*E14 -> 79691.699 | H14: =G14*F14 -> 108611.52 | I14: =RANDBETWEEN(100000,500000) -> 446639 | J14: =R14/K14 -> 28.022931 | K14: =G14/I14 -> 0.1784253 | L14: =K14*F14 -> 0.24317519 | M14: =N14*F14 -> 2.0856859 | N14: =(RAND() * (0.6 - 0.05)+0.05) *R14 -> 1.5303335 | O14: =P14*F14 -> 4.7287958 | P14: =R14-N14 -> 3.4696665 | Q14: =R15*F14 -> 0 | R14: =RANDBETWEEN(0.5,8)*5 -> 5 | S14: =I14/(1000000*J14) -> 0.01593834 | T14: =IF(W14>0,V14+RANDBETWEEN(5,20),"") | U14: =IF(V14="",RANDBETWEEN(DATE(2016,12,1),DATE(2021,12,31)),V14) -> 43707 | V14: =IF(W14>0,RANDBETWEEN(DATE(2016,12,1),DATE(2021,12,31)),"") | W14: 0 | X14: =VLOOKUP(IF(V14="",U14,V14),'US CPI'!$A$2:$C$178,3,TRUE) -> 1.2659905 | Y14: =W14*X14 -> 0 | Z14: =W14/AB14 -> 0 | AA14: =(AE14/AB14)+J14 -> 32.410099 | AB14: =K14* (AI14* (0.8 + RAND() * 0.4 ) / R14) -> 0.083760722 | AC14: =AB14*X14 -> 0.10604028 | AD14: =AE14*X14 -> 0.46521651 | AE14: =(RAND() * (0.25 - 0.05)+0.05) *AI14 -> 0.36747235 | AF14: =AH14-AD14 -> 2.0857035 | AG14: =AI14-AE14 -> 1.6474875 | AH14: =AI14*X14 -> 2.55092 | AI14: =IF(RAND()>0.45,RAND()*(1-0.4)+0.4*R14,(1+14*RAND())*R14) -> 2.0149598 | AJ14: =(Z14+I14)/(1000000*AA14) -> 0.013780859 | AK14: =AI14*1000000*AJ14 -> 27767.877 | AL14: =AK14*X14 -> 35153.869 | AM14: =(G14+W14)/SUM($G$5:$G$14,$W$5:$W$14) -> 0.0081134763 | AN14: =AK14/(G14+W14) -> 0.34844127 | AO14: =AK14/(G14+X14) -> 0.34843573 | AP14: =I14*AB14/G14 -> 0.46944419 | AQ14: =H14*AB14/G14 -> 0.11415718 | AR14: EdTech
A18: Tasks:
A19: 1. Analyze and prepare the dataset.
A20: 2. Create an analytical dashboard showcasing your findings and insights.
